setup.py
json2simplejson/__init__.py
json2simplejson.egg-info/PKG-INFO
json2simplejson.egg-info/SOURCES.txt
json2simplejson.egg-info/dependency_links.txt
json2simplejson.egg-info/requires.txt
json2simplejson.egg-info/top_level.txt