Metadata-Version: 1.0
Name: json2simplejson
Version: 1.0.0
Summary: A simple monkey patcher in order to make things that run using the standard "json" library (such as discord.py) use the quicker "simplejson" library.
Home-page: https://jakegealer.me
Author: Jake Gealer
Author-email: jake@gealer.email
License: GPL-3.0
Platform: UNKNOWN
